keystone_keycloak_backend/__init__.py
keystone_keycloak_backend/config.py
keystone_keycloak_backend/identity.py
keystone_keycloak_backend-0.4.0.dist-info/METADATA
keystone_keycloak_backend-0.4.0.dist-info/WHEEL
keystone_keycloak_backend-0.4.0.dist-info/entry_points.txt
keystone_keycloak_backend-0.4.0.dist-info/RECORD
