Metadata-Version: 2.4
Name: keystone-keycloak-backend
Version: 0.4.0
Summary: Keycloak backend for OpenStack Keystone
License: Apache-2.0
Author: Mohammed Naser
Author-email: mnaser@vexxhost.com
Requires-Python: >=3.8,<4.0
Classifier: License :: OSI Approved :: Apache Software License
Classifier: Programming Language :: Python :: 3
Classifier: Programming Language :: Python :: 3.8
Classifier: Programming Language :: Python :: 3.9
Classifier: Programming Language :: Python :: 3.10
Classifier: Programming Language :: Python :: 3.11
Classifier: Programming Language :: Python :: 3.12
Classifier: Programming Language :: Python :: 3.13
Classifier: Programming Language :: Python :: 3.14
Requires-Dist: python-keycloak (>=3.6.1,<4.0.0)
Requires-Dist: tenacity (>=6.3.1,<9.2.0)
